[
    {
        "name": "tag",
        "description": "Tags",
        "default_permission": false,
        "options": [
            {
                "type": 1,
                "name": "remove",
                "description": "Remove a tag",
                "options": [
                    {
                        "type": 3,
                        "name": "name",
                        "description": "Name of the tag",
                        "required": true
                    }
                ]
            },
            {
                "type": 1,
                "name": "show",
                "description": "Show a tag",
                "options": [
                    {
                        "type": 3,
                        "name": "name",
                        "description": "Name of the tag",
                        "required": true
                    },
                    {
                        "type": 3,
                        "name": "args",
                        "description": "Arguments for the tag",
                        "required": false
                    }
                ]
            },
            {
                "type": 1,
                "name": "create",
                "description": "Create a new tag",
                "options": [
                    {
                        "type": 3,
                        "name": "name",
                        "description": "The name of the tag",
                        "required": true
                    },
                    {
                        "type": 3,
                        "name": "content",
                        "description": "The content of the tag",
                        "required": true
                    }
                ]
            }
        ]
    }
]